dooray/Dooray.py
dooray/DoorayExceptions.py
dooray/DoorayObjects.py
dooray/IncomingHook.py
dooray/Member.py
dooray/Messenger.py
dooray/MessengerHook.py
dooray/Project.py
dooray/__init__.py
PyDooray-0.2.0.dist-info/LICENSE
PyDooray-0.2.0.dist-info/METADATA
PyDooray-0.2.0.dist-info/WHEEL
PyDooray-0.2.0.dist-info/top_level.txt
PyDooray-0.2.0.dist-info/RECORD
