Metadata-Version: 2.1
Name: PyDooray
Version: 0.2.0
Summary: Use Dooray! API
Home-page: https://github.com/iizs/PyDooray
Author: Kirin Choi
Author-email: choi.kirin@gmail.com
License: UNKNOWN
Project-URL: Bug Tracker, https://github.com/iizs/PyDooray/issues
Platform: UNKNOWN
Classifier: Development Status :: 3 - Alpha
Classifier: Programming Language :: Python :: 3
Classifier: License :: OSI Approved :: MIT License
Classifier: Operating System :: OS Independent
Requires-Python: >=3.6
License-File: LICENSE
Requires-Dist: requests (>=2.14.0)
